{
    "summary": {
        "total_runs": 16,
        "total_success": 11,
        "total_failed": 35,
        "logic_failures": 3
    },
    "runs": [
        {
            "timestamp": "2026-02-09 17:13:25",
            "total_success": 1,
            "total_failed": 2,
            "logic_failures": 0,
            "attempts": [
                {
                    "attempt_no": 1,
                    "label": "WRONG email + WRONG password",
                    "email": "fakeuser@test.com",
                    "password": "******",
                    "login_success": false,
                    "expected_login": false,
                    "test_case_success": true,
                    "error_messages": [
                        "Invalid username or password.",
                        "Invalid username or password."
                    ],
                    "url": "https://admin.dev.xuno.co/"
                },
                {
                    "attempt_no": 2,
                    "label": "REAL email + WRONG password",
                    "email": "Aryan@xuno.co",
                    "password": "******",
                    "login_success": false,
                    "expected_login": false,
                    "test_case_success": true,
                    "error_messages": [
                        "Incorrect username or password. You have 4 attempt(s) left or else your account will be locked."
                    ],
                    "url": "https://admin.dev.xuno.co/"
                },
                {
                    "attempt_no": 3,
                    "label": "REAL email + REAL password",
                    "email": "Aryan@xuno.co",
                    "password": "******",
                    "login_success": true,
                    "expected_login": true,
                    "test_case_success": true,
                    "error_messages": [],
                    "url": "https://admin.dev.xuno.co/dashboard/home"
                }
            ]
        },
        {
            "timestamp": "2026-02-09 17:23:17",
            "total_success": 1,
            "total_failed": 2,
            "logic_failures": 0,
            "attempts": [
                {
                    "attempt_no": 1,
                    "label": "WRONG email + WRONG password",
                    "email": "fakeuser@test.com",
                    "password": "******",
                    "login_success": false,
                    "expected_login": false,
                    "test_case_success": true,
                    "error_messages": [
                        "Invalid username or password.",
                        "Invalid username or password."
                    ],
                    "url": "https://admin.dev.xuno.co/"
                },
                {
                    "attempt_no": 2,
                    "label": "REAL email + WRONG password",
                    "email": "Aryan@xuno.co",
                    "password": "******",
                    "login_success": false,
                    "expected_login": false,
                    "test_case_success": true,
                    "error_messages": [
                        "Incorrect username or password. You have 4 attempt(s) left or else your account will be locked."
                    ],
                    "url": "https://admin.dev.xuno.co/"
                },
                {
                    "attempt_no": 3,
                    "label": "REAL email + REAL password",
                    "email": "Aryan@xuno.co",
                    "password": "******",
                    "login_success": true,
                    "expected_login": true,
                    "test_case_success": true,
                    "error_messages": [],
                    "url": "https://admin.dev.xuno.co/dashboard/home"
                }
            ]
        },
        {
            "timestamp": "2026-02-10 11:45:25",
            "total_success": 1,
            "total_failed": 2,
            "logic_failures": 0,
            "attempts": [
                {
                    "attempt_no": 1,
                    "label": "WRONG email + WRONG password",
                    "email": "fakeuser@test.com",
                    "password": "******",
                    "login_success": false,
                    "expected_login": false,
                    "test_case_success": true,
                    "error_messages": [
                        "Invalid username or password.",
                        "Invalid username or password."
                    ],
                    "url": "https://admin.dev.xuno.co/"
                },
                {
                    "attempt_no": 2,
                    "label": "REAL email + WRONG password",
                    "email": "Aryan@xuno.co",
                    "password": "******",
                    "login_success": false,
                    "expected_login": false,
                    "test_case_success": true,
                    "error_messages": [
                        "Incorrect username or password. You have 4 attempt(s) left or else your account will be locked."
                    ],
                    "url": "https://admin.dev.xuno.co/"
                },
                {
                    "attempt_no": 3,
                    "label": "REAL email + REAL password",
                    "email": "Aryan@xuno.co",
                    "password": "******",
                    "login_success": true,
                    "expected_login": true,
                    "test_case_success": true,
                    "error_messages": [],
                    "url": "https://admin.dev.xuno.co/dashboard/home"
                }
            ]
        },
        {
            "timestamp": "2026-02-10 12:00:12",
            "total_success": 0,
            "total_failed": 2,
            "logic_failures": 0,
            "attempts": [
                {
                    "attempt_no": 1,
                    "label": "WRONG email + WRONG password",
                    "email": "fakeuser@test.com",
                    "password": "******",
                    "login_success": false,
                    "expected_login": false,
                    "test_case_success": true,
                    "error_messages": [
                        "Invalid username or password.",
                        "Invalid username or password."
                    ],
                    "url": "https://admin.dev.xuno.co/"
                },
                {
                    "attempt_no": 2,
                    "label": "REAL email + WRONG password",
                    "email": "Aryan@xuno.co",
                    "password": "******",
                    "login_success": false,
                    "expected_login": false,
                    "test_case_success": true,
                    "error_messages": [
                        "Incorrect username or password. You have 4 attempt(s) left or else your account will be locked."
                    ],
                    "url": "https://admin.dev.xuno.co/"
                }
            ]
        },
        {
            "timestamp": "2026-02-10 12:02:20",
            "total_success": 0,
            "total_failed": 2,
            "logic_failures": 0,
            "attempts": [
                {
                    "attempt_no": 1,
                    "label": "WRONG email + WRONG password",
                    "email": "fakeuser@test.com",
                    "password": "******",
                    "login_success": false,
                    "expected_login": false,
                    "test_case_success": true,
                    "error_messages": [
                        "Invalid username or password.",
                        "Invalid username or password."
                    ],
                    "url": "https://admin.dev.xuno.co/"
                },
                {
                    "attempt_no": 2,
                    "label": "REAL email + WRONG password",
                    "email": "Aryan@xuno.co",
                    "password": "******",
                    "login_success": false,
                    "expected_login": false,
                    "test_case_success": true,
                    "error_messages": [
                        "Incorrect username or password. You have 3 attempt(s) left or else your account will be locked."
                    ],
                    "url": "https://admin.dev.xuno.co/"
                }
            ]
        },
        {
            "timestamp": "2026-02-10 12:04:35",
            "total_success": 0,
            "total_failed": 3,
            "logic_failures": 1,
            "attempts": [
                {
                    "attempt_no": 1,
                    "label": "WRONG email + WRONG password",
                    "email": "fakeuser@test.com",
                    "password": "******",
                    "login_success": false,
                    "expected_login": false,
                    "test_case_success": true,
                    "error_messages": [],
                    "url": "https://admin.dev.xuno.co/"
                },
                {
                    "attempt_no": 2,
                    "label": "REAL email + WRONG password",
                    "email": "Aryan@xuno.co",
                    "password": "******",
                    "login_success": false,
                    "expected_login": false,
                    "test_case_success": true,
                    "error_messages": [],
                    "url": "https://admin.dev.xuno.co/"
                },
                {
                    "attempt_no": 3,
                    "label": "REAL email + REAL password",
                    "email": "Aryan@xuno.co",
                    "password": "******",
                    "login_success": false,
                    "expected_login": true,
                    "test_case_success": false,
                    "error_messages": [],
                    "url": "https://admin.dev.xuno.co/"
                }
            ]
        },
        {
            "timestamp": "2026-02-10 12:11:57",
            "total_success": 0,
            "total_failed": 3,
            "logic_failures": 1,
            "attempts": [
                {
                    "attempt_no": 1,
                    "label": "WRONG email + WRONG password",
                    "email": "fakeuser@test.com",
                    "password": "******",
                    "login_success": false,
                    "expected_login": false,
                    "test_case_success": true,
                    "error_messages": [],
                    "url": "https://admin.dev.xuno.co/"
                },
                {
                    "attempt_no": 2,
                    "label": "REAL email + WRONG password",
                    "email": "Aryan@xuno.co",
                    "password": "******",
                    "login_success": false,
                    "expected_login": false,
                    "test_case_success": true,
                    "error_messages": [],
                    "url": "https://admin.dev.xuno.co/"
                },
                {
                    "attempt_no": 3,
                    "label": "REAL email + REAL password",
                    "email": "Aryan@xuno.co",
                    "password": "******",
                    "login_success": false,
                    "expected_login": true,
                    "test_case_success": false,
                    "error_messages": [],
                    "url": "https://admin.dev.xuno.co/"
                }
            ]
        },
        {
            "timestamp": "2026-02-10 13:16:57",
            "total_success": 1,
            "total_failed": 2,
            "logic_failures": 0,
            "attempts": [
                {
                    "attempt_no": 1,
                    "label": "WRONG email + WRONG password",
                    "email": "fakeuser@test.com",
                    "password": "******",
                    "login_success": false,
                    "expected_login": false,
                    "test_case_success": true,
                    "error_messages": [
                        "Invalid username or password.",
                        "Invalid username or password."
                    ],
                    "url": "https://admin.dev.xuno.co/"
                },
                {
                    "attempt_no": 2,
                    "label": "REAL email + WRONG password",
                    "email": "Aryan@xuno.co",
                    "password": "******",
                    "login_success": false,
                    "expected_login": false,
                    "test_case_success": true,
                    "error_messages": [
                        "Incorrect username or password. You have 2 attempt(s) left or else your account will be locked."
                    ],
                    "url": "https://admin.dev.xuno.co/"
                },
                {
                    "attempt_no": 3,
                    "label": "REAL email + REAL password",
                    "email": "Aryan@xuno.co",
                    "password": "******",
                    "login_success": true,
                    "expected_login": true,
                    "test_case_success": true,
                    "error_messages": [],
                    "url": "https://admin.dev.xuno.co/dashboard/home"
                }
            ]
        },
        {
            "timestamp": "2026-02-10 17:05:33",
            "total_success": 1,
            "total_failed": 2,
            "logic_failures": 0,
            "attempts": [
                {
                    "attempt_no": 1,
                    "label": "WRONG email + WRONG password",
                    "email": "fakeuser@test.com",
                    "password": "******",
                    "login_success": false,
                    "expected_login": false,
                    "test_case_success": true,
                    "error_messages": [
                        "Invalid username or password.",
                        "Invalid username or password."
                    ],
                    "url": "https://admin.dev.xuno.co/"
                },
                {
                    "attempt_no": 2,
                    "label": "REAL email + WRONG password",
                    "email": "Aryan@xuno.co",
                    "password": "******",
                    "login_success": false,
                    "expected_login": false,
                    "test_case_success": true,
                    "error_messages": [
                        "Incorrect username or password. You have 4 attempt(s) left or else your account will be locked."
                    ],
                    "url": "https://admin.dev.xuno.co/"
                },
                {
                    "attempt_no": 3,
                    "label": "REAL email + REAL password",
                    "email": "Aryan@xuno.co",
                    "password": "******",
                    "login_success": true,
                    "expected_login": true,
                    "test_case_success": true,
                    "error_messages": [],
                    "url": "https://admin.dev.xuno.co/dashboard/home"
                }
            ]
        },
        {
            "timestamp": "2026-02-11 11:16:00",
            "total_success": 0,
            "total_failed": 3,
            "logic_failures": 1,
            "attempts": [
                {
                    "attempt_no": 1,
                    "label": "WRONG email + WRONG password",
                    "email": "fakeuser@test.com",
                    "password": "******",
                    "login_success": false,
                    "expected_login": false,
                    "test_case_success": true,
                    "error_messages": [],
                    "url": "https://admin.dev.xuno.co/"
                },
                {
                    "attempt_no": 2,
                    "label": "REAL email + WRONG password",
                    "email": "Aryan@xuno.co",
                    "password": "******",
                    "login_success": false,
                    "expected_login": false,
                    "test_case_success": true,
                    "error_messages": [],
                    "url": "https://admin.dev.xuno.co/"
                },
                {
                    "attempt_no": 3,
                    "label": "REAL email + REAL password",
                    "email": "Aryan@xuno.co",
                    "password": "******",
                    "login_success": false,
                    "expected_login": true,
                    "test_case_success": false,
                    "error_messages": [],
                    "url": "https://admin.dev.xuno.co/"
                }
            ]
        },
        {
            "timestamp": "2026-02-11 11:24:30",
            "total_success": 1,
            "total_failed": 2,
            "logic_failures": 0,
            "attempts": [
                {
                    "attempt_no": 1,
                    "label": "WRONG email + WRONG password",
                    "email": "fakeuser@test.com",
                    "password": "******",
                    "login_success": false,
                    "expected_login": false,
                    "test_case_success": true,
                    "error_messages": [
                        "Invalid username or password.",
                        "Invalid username or password."
                    ],
                    "url": "https://admin.dev.xuno.co/"
                },
                {
                    "attempt_no": 2,
                    "label": "REAL email + WRONG password",
                    "email": "Aryan@xuno.co",
                    "password": "******",
                    "login_success": false,
                    "expected_login": false,
                    "test_case_success": true,
                    "error_messages": [
                        "Incorrect username or password. You have 4 attempt(s) left or else your account will be locked."
                    ],
                    "url": "https://admin.dev.xuno.co/"
                },
                {
                    "attempt_no": 3,
                    "label": "REAL email + REAL password",
                    "email": "Aryan@xuno.co",
                    "password": "******",
                    "login_success": true,
                    "expected_login": true,
                    "test_case_success": true,
                    "error_messages": [],
                    "url": "https://admin.dev.xuno.co/dashboard/home"
                }
            ]
        },
        {
            "timestamp": "2026-02-11 11:32:03",
            "total_success": 1,
            "total_failed": 2,
            "logic_failures": 0,
            "attempts": [
                {
                    "attempt_no": 1,
                    "label": "WRONG email + WRONG password",
                    "email": "fakeuser@test.com",
                    "password": "******",
                    "login_success": false,
                    "expected_login": false,
                    "test_case_success": true,
                    "error_messages": [
                        "Invalid username or password.",
                        "Invalid username or password."
                    ],
                    "url": "https://admin.dev.xuno.co/"
                },
                {
                    "attempt_no": 2,
                    "label": "REAL email + WRONG password",
                    "email": "Aryan@xuno.co",
                    "password": "******",
                    "login_success": false,
                    "expected_login": false,
                    "test_case_success": true,
                    "error_messages": [
                        "Incorrect username or password. You have 4 attempt(s) left or else your account will be locked."
                    ],
                    "url": "https://admin.dev.xuno.co/"
                },
                {
                    "attempt_no": 3,
                    "label": "REAL email + REAL password",
                    "email": "Aryan@xuno.co",
                    "password": "******",
                    "login_success": true,
                    "expected_login": true,
                    "test_case_success": true,
                    "error_messages": [],
                    "url": "https://admin.dev.xuno.co/dashboard/home"
                }
            ]
        },
        {
            "timestamp": "2026-02-11 11:39:10",
            "total_success": 1,
            "total_failed": 2,
            "logic_failures": 0,
            "attempts": [
                {
                    "attempt_no": 1,
                    "label": "WRONG email + WRONG password",
                    "email": "fakeuser@test.com",
                    "password": "******",
                    "login_success": false,
                    "expected_login": false,
                    "test_case_success": true,
                    "error_messages": [
                        "Invalid username or password.",
                        "Invalid username or password."
                    ],
                    "url": "https://admin.dev.xuno.co/"
                },
                {
                    "attempt_no": 2,
                    "label": "REAL email + WRONG password",
                    "email": "Aryan@xuno.co",
                    "password": "******",
                    "login_success": false,
                    "expected_login": false,
                    "test_case_success": true,
                    "error_messages": [
                        "Incorrect username or password. You have 4 attempt(s) left or else your account will be locked."
                    ],
                    "url": "https://admin.dev.xuno.co/"
                },
                {
                    "attempt_no": 3,
                    "label": "REAL email + REAL password",
                    "email": "Aryan@xuno.co",
                    "password": "******",
                    "login_success": true,
                    "expected_login": true,
                    "test_case_success": true,
                    "error_messages": [],
                    "url": "https://admin.dev.xuno.co/dashboard/home"
                }
            ]
        },
        {
            "timestamp": "2026-02-11 11:42:46",
            "total_success": 1,
            "total_failed": 2,
            "logic_failures": 0,
            "attempts": [
                {
                    "attempt_no": 1,
                    "label": "WRONG email + WRONG password",
                    "email": "fakeuser@test.com",
                    "password": "******",
                    "login_success": false,
                    "expected_login": false,
                    "test_case_success": true,
                    "error_messages": [
                        "Invalid username or password.",
                        "Invalid username or password."
                    ],
                    "url": "https://admin.dev.xuno.co/"
                },
                {
                    "attempt_no": 2,
                    "label": "REAL email + WRONG password",
                    "email": "Aryan@xuno.co",
                    "password": "******",
                    "login_success": false,
                    "expected_login": false,
                    "test_case_success": true,
                    "error_messages": [
                        "Incorrect username or password. You have 4 attempt(s) left or else your account will be locked."
                    ],
                    "url": "https://admin.dev.xuno.co/"
                },
                {
                    "attempt_no": 3,
                    "label": "REAL email + REAL password",
                    "email": "Aryan@xuno.co",
                    "password": "******",
                    "login_success": true,
                    "expected_login": true,
                    "test_case_success": true,
                    "error_messages": [],
                    "url": "https://admin.dev.xuno.co/dashboard/home"
                }
            ]
        },
        {
            "timestamp": "2026-02-11 11:48:06",
            "total_success": 1,
            "total_failed": 2,
            "logic_failures": 0,
            "attempts": [
                {
                    "attempt_no": 1,
                    "label": "WRONG email + WRONG password",
                    "email": "fakeuser@test.com",
                    "password": "******",
                    "login_success": false,
                    "expected_login": false,
                    "test_case_success": true,
                    "error_messages": [
                        "Invalid username or password.",
                        "Invalid username or password."
                    ],
                    "url": "https://admin.dev.xuno.co/"
                },
                {
                    "attempt_no": 2,
                    "label": "REAL email + WRONG password",
                    "email": "Aryan@xuno.co",
                    "password": "******",
                    "login_success": false,
                    "expected_login": false,
                    "test_case_success": true,
                    "error_messages": [
                        "Incorrect username or password. You have 4 attempt(s) left or else your account will be locked."
                    ],
                    "url": "https://admin.dev.xuno.co/"
                },
                {
                    "attempt_no": 3,
                    "label": "REAL email + REAL password",
                    "email": "Aryan@xuno.co",
                    "password": "******",
                    "login_success": true,
                    "expected_login": true,
                    "test_case_success": true,
                    "error_messages": [],
                    "url": "https://admin.dev.xuno.co/dashboard/home"
                }
            ]
        },
        {
            "timestamp": "2026-02-11 15:03:39",
            "total_success": 1,
            "total_failed": 2,
            "logic_failures": 0,
            "attempts": [
                {
                    "attempt_no": 1,
                    "label": "WRONG email + WRONG password",
                    "email": "fakeuser@test.com",
                    "password": "******",
                    "login_success": false,
                    "expected_login": false,
                    "test_case_success": true,
                    "error_messages": [
                        "Invalid username or password.",
                        "Invalid username or password."
                    ],
                    "url": "https://admin.dev.xuno.co/"
                },
                {
                    "attempt_no": 2,
                    "label": "REAL email + WRONG password",
                    "email": "Aryan@xuno.co",
                    "password": "******",
                    "login_success": false,
                    "expected_login": false,
                    "test_case_success": true,
                    "error_messages": [
                        "Incorrect username or password. You have 4 attempt(s) left or else your account will be locked."
                    ],
                    "url": "https://admin.dev.xuno.co/"
                },
                {
                    "attempt_no": 3,
                    "label": "REAL email + REAL password",
                    "email": "Aryan@xuno.co",
                    "password": "******",
                    "login_success": true,
                    "expected_login": true,
                    "test_case_success": true,
                    "error_messages": [],
                    "url": "https://admin.dev.xuno.co/dashboard/home"
                }
            ]
        }
    ]
}